LICENSE.txt
MANIFEST.in
README.rst
setup.py
emailage/__init__.py
emailage/api.py
emailage/exceptions.py
emailage/tools.py
emailage.egg-info/PKG-INFO
emailage.egg-info/SOURCES.txt
emailage.egg-info/dependency_links.txt
emailage.egg-info/requires.txt
emailage.egg-info/top_level.txt