Metadata-Version: 1.1
Name: emailage
Version: 1.1.2
Summary: A Python EmailAge API Wrapper
Home-page: http://www.github.com/radzhome
Author: radzhome
Author-email: UNKNOWN
License: BSD
Download-URL: http://pypi.python.org/pypi/emailage/
Keywords: emailAge api wrapper
Platform: Platform Independent
Classifier: Development Status :: 5 - Production/Stable
Classifier: Intended Audience :: Developers
Classifier: License :: OSI Approved :: BSD License
Classifier: Natural Language :: English
Classifier: Operating System :: OS Independent
Classifier: Programming Language :: Python
Classifier: Topic :: Software Development :: Libraries :: Python Modules
Requires: requests
